SideJITServer/__init__.py
SideJITServer/__main__.py
SideJITServer/_version.py
SideJITServer/launch.py
SideJITServer-1.4.2.dist-info/LICENSE
SideJITServer-1.4.2.dist-info/METADATA
SideJITServer-1.4.2.dist-info/WHEEL
SideJITServer-1.4.2.dist-info/entry_points.txt
SideJITServer-1.4.2.dist-info/top_level.txt
SideJITServer-1.4.2.dist-info/RECORD
