Metadata-Version: 2.1
Name: SideJITServer
Version: 1.4.2
Summary: SideJITServer is an iOS 17 JIT enabler for Windows/macOS!
Author: khanhduytran0
Author-email: nythepegasus <me@nythepegas.us>, JoeMatt <git@joemattiello.com>
Maintainer-email: nythepegasus <me@nythepegas.us>
Project-URL: Homepage, https://github.com/nythepegasus/SideJITServer
Project-URL: Bug Reports, https://github.com/nythepegasus/SideJITServer/issues
Keywords: ios,automation,cli,jit
Classifier: Development Status :: 5 - Production/Stable
Classifier: License :: OSI Approved :: GNU General Public License v3 or later (GPLv3+)
Classifier: Operating System :: Microsoft :: Windows
Classifier: Operating System :: Microsoft :: Windows :: Windows 10
Classifier: Operating System :: Microsoft :: Windows :: Windows 11
Classifier: Operating System :: MacOS :: MacOS X
Classifier: Operating System :: iOS
Classifier: Programming Language :: Python :: 3
Classifier: Programming Language :: Python :: 3.10
Classifier: Programming Language :: Python :: 3.11
Classifier: Programming Language :: Python :: 3.12
Classifier: Programming Language :: Python :: 3 :: Only
Requires-Python: >=3.10
License-File: LICENSE
Requires-Dist: pymobiledevice3<4.19.0,>=4.18.0
Requires-Dist: zeroconf==0.132.2
Provides-Extra: dev
Requires-Dist: build; extra == "dev"
Requires-Dist: pylint; extra == "dev"
